attn_gym/__init__.py
attn_gym/utils.py
attn_gym/masks/__init__.py
attn_gym/masks/batchify.py
attn_gym/masks/causal.py
attn_gym/masks/dilated_sliding_window.py
attn_gym/masks/document_mask.py
attn_gym/masks/flamingo.py
attn_gym/masks/natten.py
attn_gym/masks/prefix_lm.py
attn_gym/masks/sliding_window.py
attn_gym/masks/sta.py
attn_gym/mods/__init__.py
attn_gym/mods/alibi.py
attn_gym/mods/latent_attention.py
attn_gym/mods/softcapping.py
attn_gym/paged_attention/latency.py
attn_gym/paged_attention/model.py
attn_gym/paged_attention/paged_attention.py
attn_gym/paged_attention/throughput.py
attn_gym/paged_attention/utils.py
attn_gym-0.0.4.dist-info/METADATA
attn_gym-0.0.4.dist-info/WHEEL
attn_gym-0.0.4.dist-info/licenses/LICENSE
attn_gym-0.0.4.dist-info/RECORD
