Metadata-Version: 2.4
Name: attn_gym
Version: 0.0.4
Summary: Helpful tools and examples for working with flex-attention
Author-email: Driss Guessous <drisspguessous@gmail.com>
License-File: LICENSE
Classifier: License :: OSI Approved :: BSD License
Classifier: Operating System :: OS Independent
Classifier: Programming Language :: Python :: 3
Requires-Python: >=3.9
Requires-Dist: torch
Provides-Extra: dev
Requires-Dist: bumpver; extra == 'dev'
Requires-Dist: docstring-parser; extra == 'dev'
Requires-Dist: jsonargparse; extra == 'dev'
Requires-Dist: pip-tools; extra == 'dev'
Requires-Dist: pre-commit==3.6.0; extra == 'dev'
Requires-Dist: pytest; extra == 'dev'
Requires-Dist: ruff; extra == 'dev'
Provides-Extra: viz
Requires-Dist: docstring-parser; extra == 'viz'
Requires-Dist: jsonargparse; extra == 'viz'
Requires-Dist: matplotlib; extra == 'viz'
Requires-Dist: numpy; extra == 'viz'
Requires-Dist: tabulate; extra == 'viz'
